9_gray2binary/gray2binary.v
`timescale 1ns/1ps

module gray2binary #(
    parameter N=4
)(
    input [N-1:0] gray,
    output [N-1:0] binary
);
    assign binary[N-1] = gray[N-1];
    
    // genvar i;
    // generate
    //     for (i = N-2; i >= 0; i = i - 1) begin : binary_logic
    //         assign binary[i] = binary[i+1] ^ gray[i];
    //     end
    // endgenerate 
    assign binary = gray ^ {1'b0, gray[N-1:1]};
endmodule

module gray2binary_tb;
    parameter N = 4;
    reg [N-1:0] gray;
    wire [N-1:0] binary;

    gray2binary #(.N(N)) gb (
        .gray(gray),
        .binary(binary)
    );

    initial begin
        $dumpfile("gray2binary.vcd");
        $dumpvars(0, gray2binary_tb);
        $monitor("Time: %0t | Gray: %b | Binary: %b", $time, gray, binary);
        gray = 4'b0000;
        repeat (15) begin
            #10 gray = gray + 1;
        end
        #10 $finish;
    end
endmodule

9_gray2binary/gray2binary.vcd
$date
	Sat May 10 20:34:20 2025
$end
$version
	Icarus Verilog
$end
$timescale
	1ps
$end
$scope module gray2binary_tb $end
$var wire 4 ! binary [3:0] $end
$var parameter 32 " N $end
$var reg 4 # gray [3:0] $end
$scope module gb $end
$var wire 4 $ binary [3:0] $end
$var wire 4 % gray [3:0] $end
$var parameter 32 & N $end
$upscope $end
$upscope $end
$enddefinitions $end
$comment Show the parameter values. $end
$dumpall
b100 &
b100 "
$end
#0
$dumpvars
b0 %
b0 $
b0 #
b0 !
$end
#10000
b1 !
b1 $
b1 #
b1 %
#20000
b11 !
b11 $
b10 #
b10 %
#30000
b10 !
b10 $
b11 #
b11 %
#40000
b110 !
b110 $
b100 #
b100 %
#50000
b111 !
b111 $
b101 #
b101 %
#60000
b101 !
b101 $
b110 #
b110 %
#70000
b100 !
b100 $
b111 #
b111 %
#80000
b1100 !
b1100 $
b1000 #
b1000 %
#90000
b1101 !
b1101 $
b1001 #
b1001 %
#100000
b1111 !
b1111 $
b1010 #
b1010 %
#110000
b1110 !
b1110 $
b1011 #
b1011 %
#120000
b1010 !
b1010 $
b1100 #
b1100 %
#130000
b1011 !
b1011 $
b1101 #
b1101 %
#140000
b1001 !
b1001 $
b1110 #
b1110 %
#150000
b1000 !
b1000 $
b1111 #
b1111 %
