2_fullAdder/fa.v
`timescale 1ns/1ps

module fa(input a,b,cin,
           output sum,cout);
    assign sum = a ^ b ^ cin;
    assign cout = (a & b) | (cin & (a ^ b));
endmodule

//fa much better than using ha
module ha(input a,b,
           output sum,carry);
    assign sum = a ^ b;
    assign carry = a & b;
endmodule

module fa_using_ha(input a,b,cin,
           output sum,cout);
    wire s1,c1,c2;
    ha ha1(a,b,s1,c1);
    ha ha2(s1,cin,sum,c2);
    assign cout = c1 | c2;
endmodule

// Testbench
module tb_fa;
    reg a, b, cin;
    wire sum, cout;

    fa uut (
        .a(a),
        .b(b),
        .cin(cin),
        .sum(sum),
        .cout(cout)
    );

    initial begin
        $dumpfile("fa.vcd"); 
        $dumpvars(0, tb_fa);
        $monitor("a=%b, b=%b, cin=%b, sum=%b, cout=%b", a, b, cin, sum, cout);
        
       a = 0; b = 0; cin = 0; #10;
       a = 0; b = 1; cin = 0; #10;
       a = 1; b = 0; cin = 0; #10;
       a = 1; b = 1; cin = 0; #10;
       a = 0; b = 0; cin = 1; #10;
       a = 0; b = 1; cin = 1; #10;
       a = 1; b = 0; cin = 1; #10;
       a = 1; b = 1; cin = 1; #10;

        $finish;
    end
endmodule

2_fullAdder/fa.vcd
$date
	Fri May 09 20:31:00 2025
$end
$version
	Icarus Verilog
$end
$timescale
	1ps
$end
$scope module tb_fa $end
$var wire 1 ! sum $end
$var wire 1 " cout $end
$var reg 1 # a $end
$var reg 1 $ b $end
$var reg 1 % cin $end
$scope module uut $end
$var wire 1 # a $end
$var wire 1 $ b $end
$var wire 1 % cin $end
$var wire 1 " cout $end
$var wire 1 ! sum $end
$upscope $end
$upscope $end
$enddefinitions $end
$comment Show the parameter values. $end
$dumpall
$end
#0
$dumpvars
0%
0$
0#
0"
0!
$end
#10000
1!
1$
#20000
0$
1#
#30000
0!
1"
1$
#40000
0"
1!
1%
0$
0#
#50000
1"
0!
1$
#60000
0$
1#
#70000
1!
1$
